LICENSE.md
MANIFEST.in
README.md
pyproject.toml
requirements-old.txt
requirements.txt
setup.py
combo_lock/__init__.py
combo_lock/combo_lock.py
combo_lock/util.py
combo_lock.egg-info/PKG-INFO
combo_lock.egg-info/SOURCES.txt
combo_lock.egg-info/dependency_links.txt
combo_lock.egg-info/requires.txt
combo_lock.egg-info/top_level.txt
tests/test_lock.py
tests/test_named_lock.py
tests/test_util.py