Metadata-Version: 2.1
Name: combo_lock
Version: 0.3.0
Summary: A combined process and thread lock
Author-email: Åke Forslund <ake.forslund@gmail.com>, JarbasAI <jarbasai@mailfence.com>
License: Apache License v2.0
Project-URL: Repository, https://github.com/forslund/combo-lock
Project-URL: Homepage, https://github.com/forslund/combo-lock
Classifier: Development Status :: 4 - Beta
Classifier: Intended Audience :: Developers
Classifier: License :: OSI Approved :: Apache Software License
Classifier: Programming Language :: Python :: 3.5
Classifier: Programming Language :: Python :: 3.6
Classifier: Programming Language :: Python :: 3.7
Classifier: Programming Language :: Python :: 3.8
License-File: LICENSE.md
Requires-Dist: filelock~=3.0
Requires-Dist: memory-tempfile
